LICENSE
MANIFEST.in
README.rst
setup.py
django_shrink.egg-info/PKG-INFO
django_shrink.egg-info/SOURCES.txt
django_shrink.egg-info/dependency_links.txt
django_shrink.egg-info/not-zip-safe
django_shrink.egg-info/requires.txt
django_shrink.egg-info/top_level.txt
shrink/__init__.py
shrink/base.py
shrink/helpers.py
shrink/urls.py
shrink/views.py
shrink/conf/__init__.py
shrink/conf/defaults.py
shrink/management/__init__.py
shrink/management/commands/__init__.py
shrink/management/commands/collectstatic.py
shrink/shrinks/cc/COPYING
shrink/shrinks/cc/README
shrink/shrinks/cc/compiler.jar
shrink/shrinks/yui/LICENSE.TXT
shrink/shrinks/yui/yuicompressor-2.4.6.jar
shrink/templatetags/__init__.py
shrink/templatetags/shrink.py